CHANGELOG.txt
LICENSE.txt
MANIFEST.in
README.txt
ez_setup.py
setup.cfg
setup.py
StaticDispatch.egg-info/PKG-INFO
StaticDispatch.egg-info/SOURCES.txt
StaticDispatch.egg-info/dependency_links.txt
StaticDispatch.egg-info/entry_points.txt
StaticDispatch.egg-info/not-zip-safe
StaticDispatch.egg-info/requires.txt
StaticDispatch.egg-info/top_level.txt
doc/index.txt
doc/source/api.rst
doc/source/index.rst
doc/source/manual.rst
example/README.txt
staticdispatch/__init__.py
test/README.txt
test/doc.py