Metadata-Version: 1.0
Name: StaticDispatch
Version: 0.2.1
Summary: A service provider which serves static files
Home-page: http://jimmyg.org/work/code/staticdispatch/index.html
Author: James Gardner
Author-email: james@<package hompage URL>
License: GNU AGPLv3
Platform: UNKNOWN
Classifier: Development Status :: 3 - Alpha
Classifier: License :: OSI Approved :: GNU Affero General Public License v3
Classifier: Programming Language :: Python
